LICENSE
README.txt
aditam-admin.py
ez_setup.py
setup.cfg
setup.py
aditam/__init__.py
aditam.core.egg-info/PKG-INFO
aditam.core.egg-info/SOURCES.txt
aditam.core.egg-info/dependency_links.txt
aditam.core.egg-info/namespace_packages.txt
aditam.core.egg-info/not-zip-safe
aditam.core.egg-info/requires.txt
aditam.core.egg-info/top_level.txt
aditam/core/__init__.py
aditam/core/admin.py
aditam/core/agentjob.py
aditam/core/bootstrap.py
aditam/core/config.py
aditam/core/daemon.py
aditam/core/errors.py
aditam/core/conf/aditam-agent.conf-sample
aditam/core/conf/aditam-server.conf-sample
aditam/core/model/__init__.py
aditam/core/model/command.py
aditam/core/model/farmnode.py
aditam/core/model/group.py
aditam/core/model/job.py
aditam/core/model/meta.py
aditam/core/model/permission.py
aditam/core/model/report.py
aditam/core/model/task.py
aditam/core/model/user.py
debian/README.Debian
debian/changelog
debian/compat
debian/control
debian/copyright
debian/dirs
debian/docs
debian/rules