Metadata-Version: 1.0
Name: aditam.core
Version: 0.1
Summary: Automated and DIstributed TAsk Manager core part.
Home-page: http://www.aditam.org/
Author: ADITAM project
Author-email: contact@aditam.org
License: GPLv3
Keywords: tasks
Platform: UNKNOWN
Classifier: Development Status :: 2 - Pre-Alpha
Classifier: Environment :: Console
Classifier: Intended Audience :: System Administrators
Classifier: Intended Audience :: Other Audience
Classifier: License :: OSI Approved :: GNU General Public License (GPL)
Classifier: Operating System :: OS Independent
Classifier: Programming Language :: Python
